Workbook

Sheet 4637
F2: MUEBLES SANTA FE SPA
F3: VENTAS POR MENOR DE MUEBLES
F4: RUT: 77.054.606-0
F5: SEPTIMA AVENIDA 1631, SAN MIGUEL
F6: FONO 22521 6502
F7: E-MAIL: ventas@topmobili.cl
B8: P R E S U P U E S T O | D8: N° 11243 | F8: NOTA DE VENTA : | G8: 7153
B10: CLIENTE: | C10: INVERSIONES MIXXO SPA | F10: FECHA : | G10: 45666
B11: RUT: | C11: 76.625.032-7 | F11: FECHA LIMITE : | G11: 45673
B12: GIRO: | C12: VETA Y ARRIENDO DE BIENES INMUEBLES | F12: ORDEN DE COMPRA:
B13: CONTACTO: | C13: ANDREA GOMEZ | F13: HECHO POR: | G13: FERNANDO DONOSO
B14: FONO: | C14: 569 9220 8443 | F14: SERVICIO EXPRESS:
B15: DIRECCION: | C15: BICENTENARIO 4063 OF 62D VITACURA | F15: FORMA DE PAGO : | G15: CONTADO
B16: CIUDAD: | C16: SANTIAGO | F16: VALIDEZ COTIZACIÓN: 5 DÍAS
B19: D E T A L L E
B20: UNIDAD | C20: TIPO | D20: LARGO | E20: ANCHO | F20: COLOR | G20: VALOR | H20: TOTAL
B21: 1 | C21: CUB C/R R8 | D21: 3240 | E21: 600 | F21: GRIS NUBE 2189 MT | G21: 171000 | H21: =G21*B21 -> 171000
G24: NETO | H24: =SUM(H21:H23) -> 171000
G25: I.V.A. | H25: =H24*19% -> 32490
G26: TOTAL | H26: =H24+H25 -> 203490
B29: CUENTA VISTA DEL BANCO ESTADO N° 35571389078 A NOMBRE DE
B30: "MUEBLES SANTA FE SPA." - RUT : 77.054.606-0, VENTAS@TOPMOBILI.CL
B31: VISITANOS Y DESCUBRE NUESTROS PRODUCTOS EN | E31: WWW.TOPMOBILICHILE.CL

Sheet REGLAS
B2: DETALLE CORTE LAMINA | G2: DETALLE CORTE SUSTRATO | P2: DETALLE CORTE MERA
B3: ALTO | C3: ANCHO | D3: TIPO | G3: ALTO | H3: ANCHO | I3: TIPO | P3: ALTO | Q3: ANCHO | R3: TIPO
B4: 40 | C4: 60 | D4: CEN 1V | E4: A1 | G4: 50 | H4: 100 | I4: CEN 1V | J4: REGLA SIEMPRE LLEVAR MEDIDA MINIMO A 100 | P4: 50 | Q4: -30 | R4: CUB C/R
B5: 40 | C5: 90 | D5: CEN 2V | E5: A2 | G5: 50 | I5: CEN 2V | J5: REGLA SIEMPRE LLEVAR MEDIDA MINIMO A 101 | P5: 50 | Q5: -30 | R5: CUB C/R
B6: 40 | C6: 100 | D6: CORNISA FRENTE ESPAÑOL 1 LADO | E6: A3 | G6: 50 | H6: 100 | I6: CORNISA FRENTE ESPAÑOL 1 LADO | P6: 50 | Q6: -30 | R6: CUB C/R 180°
B7: 40 | C7: 150 | D7: CORNISA FRENTE ESPAÑOL 2 LADO | E7: A4 | G7: 50 | I7: CORNISA FRENTE ESPAÑOL 2 LADO | P7: 50 | Q7: -30 | R7: CUB C/R FRENTE ESPAÑOL
B8: 40 | C8: 100 | D8: CORNISA 180° 1LADO | E8: A5 | G8: 50 | H8: 100 | I8: CORNISA 180° 1LADO | L8: DETALLE CORTE MERA | P8: 50 | Q8: -30 | R8: CUB C/R PUNTA 1 LADO
B9: 40 | C9: 50 | D9: CORNISA PUNTA TIBURON 1 LADO | E9: B | G9: 50 | H9: 100 | I9: CORNISA 1LADO | L9: ALTO | M9: ANCHO | N9: TIPO | P9: 50 | Q9: 0 | R9: CUB S/R FRENTE ESPAÑOL
B10: 40 | C10: 80 | D10: CORNISA PUNTA TIBURON 2 LADOS | E10: C | G10: 50 | I10: CORNISA 2 LADOS | L10: 50 | M10: -30 | N10: CUB C/R | P10: 50 | Q10: 0 | R10: CUB S/R
B11: 40 | C11: 60 | D11: CORNISA R8 1LADO | E11: D | G11: 50 | H11: 100 | I11: CORNISA PUNTA TIBURON 1 LADO | L11: 50 | M11: 0 | N11: CUB S/R y CUB MESA | P11: 50 | Q11: 0 | R11: CUB MESA 180° 2 LADOS
B12: 40 | C12: 100 | D12: CORNISA R8 2 LADOS | E12: E | G12: 50 | I12: CORNISA PUNTA TIBURON 2 LADOS | L12: 50 | M12: -2 | N12: PR | P12: 50 | Q12: 0 | R12: CUB MESA 180° 3 LADOS
B13: 40 | C13: 130 | D13: CUB C/R R6 | E13: F | G13: 50 | H13: -30 | I13: CUB C/R | P13: 50 | Q13: 0 | R13: CUB MESA 180° 4 LADOS
B14: 40 | C14: 150 | D14: CUB C/R 180° | G14: 50 | H14: -30 | I14: CUB C/R 180°
B15: 40 | C15: 150 | D15: CUB C/R FRENTE ESPAÑOL | E15: G | G15: 50 | H15: -30 | I15: CUB C/R FRENTE ESPAÑOL | P15: 50 | Q15: 0 | R15: CUB MESA 4 LADOS
B16: 40 | C16: 130 | D16: CUB C/R R2 | E16: H | G16: 50 | H16: -30 | I16: CUB C/R PUNTA TIBURON 1 LADO | P16: 50 | Q16: 0 | R16: CUB MESA FRENTE ESPAÑOL 2 LADOS
B17: 40 | C17: 150 | D17: CUB MESA 180° 2 LADOS | E17: I | G17: 50 | I17: CUB MESA 180° 2 LADOS | P17: 50 | Q17: 0 | R17: CUB MESA FRENTE ESPAÑOL 3 LADOS
B18: 140 | C18: 150 | D18: CUB MESA 180° 3 LADOS | E18: J | G18: 50 | I18: CUB MESA 180° 3 LADOS | P18: 50 | Q18: 0 | R18: CUB MESA FRENTE ESPAÑOL 4 LADOS
B19: 150 | C19: 150 | D19: CUB MESA 180° 4 LADOS | E19: K | G19: 50 | I19: CUB MESA 180° 4 LADOS | P19: 50 | Q19: 0 | R19: CUB MESA PUNTA TIBURON 2 LADOS
B20: 40 | C20: 100 | D20: CUB MESA 2L | E20: L | G20: 50 | H20: 0 | I20: CUB MESA 2L | J20: ES IGUAL A LO PEDIDO NO SE DEBE SUMAR NI RESTAR | P20: 50 | Q20: 0 | R20: CUB MESA PUNTA TIBURON 3 LADOS
B21: 100 | C21: 100 | D21: CUB MESA 3L | E21: M | G21: 50 | H21: 0 | I21: CUB MESA 3L | P21: 50 | Q21: 0 | R21: CUB MESA PUNTA TIBURON 4 LADOS
B22: 100 | C22: 100 | D22: CUB MESA 4 LADOS | E22: N | I22: CUB MESA 4 LADOS | P22: 50 | Q22: 0 | R22: CUB PUNTA TIBURON 1 LADO
B23: 40 | C23: 150 | D23: CUB MESA FRENTE ESPAÑOL 2 LADOS | E23: O | G23: 50 | I23: CUB MESA FRENTE ESPAÑOL 2 LADOS | R23: CENEFA 1 LADO
B24: 140 | C24: 150 | D24: CUB MESA FRENTE ESPAÑOL 3 LADOS | E24: P | G24: 50 | I24: CUB MESA FRENTE ESPAÑOL 3 LADOS | R24: CENEFA 2 LADOS
B25: 150 | C25: 150 | D25: CUB MESA FRENTE ESPAÑOL 4 LADOS | E25: Q | G25: 50 | I25: CUB MESA FRENTE ESPAÑOL 4 LADOS | R25: CORNISA FRENTE ESPAÑOL 1 LADO
B26: 40 | C26: 77 | D26: CUB MESA PUNTA TIBURON 2 LADOS | E26: R | G26: 50 | I26: CUB MESA PUNTA TIBURON 2 LADOS | R26: CORNISA FRENTE ESPAÑOL 2 LADO
B27: 110 | C27: 77 | D27: CUB MESA PUNTA TIBURON 3 LADOS | E27: S | G27: 50 | I27: CUB MESA PUNTA TIBURON 3 LADOS | R27: CORNISA 180° 1LADO
B28: 120 | C28: 77 | D28: CUB MESA PUNTA TIBURON 4 LADOS | E28: T | G28: 50 | I28: CUB MESA PUNTA TIBURON 4 LADOS | R28: CORNISA 1LADO
B29: 40 | C29: 50 | D29: CUB PUNTA TIBURON 1 LADO | E29: U | G29: 50 | I29: CUB PUNTA TIBURON 1 LADO | R29: CORNISA 2 LADOS
B30: 40 | C30: 60 | D30: CUB S/R | E30: V | G30: 50 | I30: CUB S/R | R30: CORNISA PUNTA TIBURON 1 LADO
B31: 40 | C31: 100 | D31: CUB S/R FRENTE ESPAÑOL | E31: W | G31: 50 | I31: CUB S/R FRENTE ESPAÑOL | R31: CORNISA PUNTA TIBURON 2 LADOS
B32: 40 | C32: 60 | D32: CUB S/R R2 | E32: X | G32: 50 | I32: CUB S/R R2 | R32: PR2
B33: 40 | C33: 90 | D33: PR12 | E33: Y | G33: 50 | H33: -2 | I33: PR12 | R33: PR6
B34: 40 | C34: 90 | D34: PR19 | G34: 50 | H34: -2 | I34: PR19
B35: 40 | C35: 90 | D35: PR2 | E35: Z | G35: 50 | H35: -2 | I35: PR2 | R35: PR8
B36: 40 | C36: 90 | D36: PR6 | G36: 50 | H36: -2 | I36: PR6 | R36: PR12
B37: 40 | C37: 90 | D37: PR8 | G37: 50 | H37: -2 | I37: PR8 | R37: PR19
B48: 40 | C48: 150

Sheet CUBIERTA
K2: NO BORRAR REGLAS!!!!! SI NO LAS SABEN USAR NO BORREN ESTO POR FAVOR!!!!!
K3: SUSTRATO | M3: LAMINADO
C4: NOTA DE VENTA : | D4: ='4637'!G8 -> 7153 | K4: ALTO | L4: ANCHO | M4: ALTO | N4: ANCHO
C5: CLIENTE : | D5: ='4637'!C10 -> INVERSIONES MIXXO SPA | K5: =LOOKUP(#REF!,REGLAS!$I$4:$I$37,REGLAS!$G$4:$G$37)+#REF! -> #REF! | L5: =LOOKUP(#REF!,REGLAS!$I$4:$I$37,REGLAS!$H$4:$H$37)+#REF! -> #REF! | M5: =LOOKUP(#REF!,REGLAS!$D$4:$D$37,REGLAS!$B$4:$B$37)+#REF! -> #REF! | N5: =LOOKUP(#REF!,REGLAS!$D$4:$D$37,REGLAS!$C$4:$C$37)+#REF! -> #REF!
C7: ='4637'!F11 -> FECHA LIMITE : | D7: ='4637'!G11 -> 45673
C8: FECHA ENTREGA:
A10: SUSTRATO
D12: ALTO | E12: ANCHO
A13: MATERIAL | B13: CANTIDAD | C13: CORTE | D13: 80 | E13: -30 | F13: DESCRIPCIÓN | J13: ALTO | K13: ANCHO
A14: MDF 18MM | B14: =I14 -> 1 | D14: =J14+D$13 -> 3320 | E14: =K14+E13 -> 570 | F14: =C29 -> CUB C/R R8 | I14: =I22 -> 1 | J14: =D29 -> 3240 | K14: =E29 -> 600
A18: LAMINADO
D20: ALTO | E20: ANCHO
A21: MATERIAL | B21: CANTIDAD | C21: CORTE | D21: 40 | E21: 130 | F21: DESCRIPCIÓN | J21: ALTO | K21: ANCHO
A22: MDF 18MM | B22: =I22 -> 1 | D22: =J22+D$21 -> 3280 | E22: =K22+E21 -> 730 | F22: =C29 -> CUB C/R R8 | I22: =B29 -> 1 | J22: =D29 -> 3240 | K22: =E29 -> 600
B23: =I23 -> 1 | D23: 3650 | E23: 150 | F23: =C30 -> ZOCALO | I23: =B30 -> 1 | J23: =D30 -> 3650 | K23: =E30 -> 150
B26: MEDIDAS ORIGINALES
A28: MATERIAL | B28: CANTIDAD | C28: DESCRIPCIÓN | D28: ALTO | E28: ANCHO | F28: COLOR
A29: MDF18MM | B29: ='4637'!B21 -> 1 | C29: ='4637'!C21 -> CUB C/R R8 | D29: ='4637'!D21 -> 3240 | E29: ='4637'!E21 -> 600 | F29: ='4637'!F21 -> GRIS NUBE 2189 MT
B30: 1 | C30: ZOCALO | D30: 3650 | E30: 150 | F30: GRIS NUBE 2189 MT
C41: NOTA DE VENTA : | D41: ='4637'!G8 -> 7153
C42: CLIENTE : | D42: ='4637'!C10 -> INVERSIONES MIXXO SPA
C44: ='4637'!F11 -> FECHA LIMITE : | D44: ='4637'!G11 -> 45673
A47: PRODUCCIÓN
B49: DETALLE
B50: CANTIDAD | C50: CORTE | D50: ALTO | E50: ANCHO | F50: DESCRIPCION
B51: ='4637'!B21 -> 1 | C51: ='4637'!C21 -> CUB C/R R8 | D51: ='4637'!D21 -> 3240 | E51: ='4637'!E21 -> 600 | F51: ='4637'!F21 -> GRIS NUBE 2189 MT
B52: 1 | C52: ZOCALO | D52: 3650 | E52: 150 | F52: GRIS NUBE 2189 MT
