Workbook

Sheet 4637
F2: MUEBLES SANTA FE SPA
F3: VENTAS POR MENOR DE MUEBLES
F4: RUT: 77.054.606-0
F5: SEPTIMA AVENIDA 1631, SAN MIGUEL
F6: FONO 22521 6502
F7: E-MAIL: ventas@topmobili.cl
B8: P R E S U P U E S T O | D8: N° 11035 | F8: NOTA DE VENTA : | G8: 7105
B10: CLIENTE: | C10: OSCAR LOPEZ | F10: FECHA : | G10: 45537
B11: RUT: | F11: FECHA LIMITE : | G11: 45540
B12: GIRO:
B13: CONTACTO: | F13: ORDEN DE COMPRA:
B14: CORREO: | F14: HECHO POR: | G14: F.D.
B15: FONO: | C15: +569 7150 2245 | F15: SERVICIO EXPRESS: | G15: NO
B16: DIRECCION: | F16: FORMA DE PAGO : | G16: ABONO 50% SALDO C/ENTREGA
B17: CIUDAD: | C17: VILLARRICA | F17: VALIDEZ COTIZACIÓN: 5 DÍAS
B20: D E T A L L E
B21: UNIDAD | C21: TIPO | D21: LARGO | E21: ANCHO | F21: COLOR | G21: VALOR | H21: TOTAL | L21: 45000
B22: 1 | C22: CUBIERTA MESA 2 LADOS R2 | D22: 2100 | E22: 740 | F22: MARINA DI CARRARA | G22: 147044 | H22: =G22*B22 -> 147044 | L22: =L21*2.5 -> 112500 | N22: 108700
B23: 1 | C23: CUB SIN RESPALDO R2 | D23: 2670 | E23: 630 | F23: MARINA DI CARRARA | G23: 158375 | H23: =G23*B23 -> 158375
B24: 1 | C24: CUB SIN RESPALDO R2 | D24: 2295 | E24: 580 | F24: MARINA DI CARRARA | G24: 125704 | H24: =G24*B24 -> 125704
B25: 1 | C25: CUB SIN RESPALDO R2 | D25: 1250 | E25: 450 | F25: MARINA DI CARRARA | G25: 51664 | H25: =G25*B25 -> 51664
B26: 1 | C26: RESPALDO | D26: 2295 | E26: 70 | F26: MARINA DI CARRARA | G26: 15171 | H26: =G26*B26 -> 15171
B27: 1 | C27: RESPALDO | D27: 2670 | E27: 70 | F27: MARINA DI CARRARA | G27: 17597 | H27: =G27*B27 -> 17597
B28: 1 | C28: RESPALDO | D28: 1250 | E28: 70 | F28: MARINA DI CARRARA | G28: 8410 | H28: =G28*B28 -> 8410 | P28: 2940 | Q28: 600 | S28: 162x132
G29: SUBTOTAL | H29: 523965
G30: DESCTO. 5% | H30: -25814
G31: NETO | H31: =H29+H30 -> 498151
G32: IVA | H32: =H31*0.19 -> 94648.69 | P32: 1890 | Q32: 600
G33: TOTAL | H33: =H31+H32 -> 592799.69
B36: CUENTA VISTA DEL BANCO ESTADO N° 35571389078 A NOMBRE DE
B37: "MUEBLES SANTA FE SPA." - RUT : 77.054.606-0, VENTAS@TOPMOBILI.CL
B38: VISITANOS Y DESCUBRE NUESTROS PRODUCTOS EN | E38: WWW.TOPMOBILICHILE.CL

Sheet REGLAS
B2: DETALLE CORTE LAMINA | G2: DETALLE CORTE SUSTRATO | P2: DETALLE CORTE MERA
B3: ALTO | C3: ANCHO | D3: TIPO | G3: ALTO | H3: ANCHO | I3: TIPO | P3: ALTO | Q3: ANCHO | R3: TIPO
B4: 40 | C4: 60 | D4: CEN 1V | E4: A1 | G4: 50 | H4: 100 | I4: CEN 1V | J4: REGLA SIEMPRE LLEVAR MEDIDA MINIMO A 100 | P4: 50 | Q4: -30 | R4: CUB C/R
B5: 40 | C5: 90 | D5: CEN 2V | E5: A2 | G5: 50 | I5: CEN 2V | J5: REGLA SIEMPRE LLEVAR MEDIDA MINIMO A 101 | P5: 50 | Q5: -30 | R5: CUB C/R
B6: 40 | C6: 100 | D6: CORNISA FRENTE ESPAÑOL 1 LADO | E6: A3 | G6: 50 | H6: 100 | I6: CORNISA FRENTE ESPAÑOL 1 LADO | P6: 50 | Q6: -30 | R6: CUB C/R 180°
B7: 40 | C7: 150 | D7: CORNISA FRENTE ESPAÑOL 2 LADO | E7: A4 | G7: 50 | I7: CORNISA FRENTE ESPAÑOL 2 LADO | P7: 50 | Q7: -30 | R7: CUB C/R FRENTE ESPAÑOL
B8: 40 | C8: 100 | D8: CORNISA 180° 1LADO | E8: A5 | G8: 50 | H8: 100 | I8: CORNISA 180° 1LADO | L8: DETALLE CORTE MERA | P8: 50 | Q8: -30 | R8: CUB C/R PUNTA 1 LADO
B9: 40 | C9: 50 | D9: CORNISA PUNTA TIBURON 1 LADO | E9: B | G9: 50 | H9: 100 | I9: CORNISA 1LADO | L9: ALTO | M9: ANCHO | N9: TIPO | P9: 50 | Q9: 0 | R9: CUB S/R FRENTE ESPAÑOL
B10: 40 | C10: 80 | D10: CORNISA PUNTA TIBURON 2 LADOS | E10: C | G10: 50 | I10: CORNISA 2 LADOS | L10: 50 | M10: -30 | N10: CUB C/R | P10: 50 | Q10: 0 | R10: CUB S/R
B11: 40 | C11: 60 | D11: CORNISA R8 1LADO | E11: D | G11: 50 | H11: 100 | I11: CORNISA PUNTA TIBURON 1 LADO | L11: 50 | M11: 0 | N11: CUB S/R y CUB MESA | P11: 50 | Q11: 0 | R11: CUB MESA 180° 2 LADOS
B12: 40 | C12: 100 | D12: CORNISA R8 2 LADOS | E12: E | G12: 50 | I12: CORNISA PUNTA TIBURON 2 LADOS | L12: 50 | M12: -2 | N12: PR | P12: 50 | Q12: 0 | R12: CUB MESA 180° 3 LADOS
B13: 40 | C13: 130 | D13: CUB C/R R6 | E13: F | G13: 50 | H13: -30 | I13: CUB C/R | P13: 50 | Q13: 0 | R13: CUB MESA 180° 4 LADOS
B14: 40 | C14: 150 | D14: CUB C/R 180° | G14: 50 | H14: -30 | I14: CUB C/R 180°
B15: 40 | C15: 150 | D15: CUB C/R FRENTE ESPAÑOL | E15: G | G15: 50 | H15: -30 | I15: CUB C/R FRENTE ESPAÑOL | P15: 50 | Q15: 0 | R15: CUB MESA 4 LADOS
B16: 40 | C16: 130 | D16: CUB C/R R2 | E16: H | G16: 50 | H16: -30 | I16: CUB C/R PUNTA TIBURON 1 LADO | P16: 50 | Q16: 0 | R16: CUB MESA FRENTE ESPAÑOL 2 LADOS
B17: 40 | C17: 150 | D17: CUB MESA 180° 2 LADOS | E17: I | G17: 50 | I17: CUB MESA 180° 2 LADOS | P17: 50 | Q17: 0 | R17: CUB MESA FRENTE ESPAÑOL 3 LADOS
B18: 140 | C18: 150 | D18: CUB MESA 180° 3 LADOS | E18: J | G18: 50 | I18: CUB MESA 180° 3 LADOS | P18: 50 | Q18: 0 | R18: CUB MESA FRENTE ESPAÑOL 4 LADOS
B19: 150 | C19: 150 | D19: CUB MESA 180° 4 LADOS | E19: K | G19: 50 | I19: CUB MESA 180° 4 LADOS | P19: 50 | Q19: 0 | R19: CUB MESA PUNTA TIBURON 2 LADOS
B20: 40 | C20: 100 | D20: CUB MESA 2L | E20: L | G20: 50 | H20: 0 | I20: CUB MESA 2L | J20: ES IGUAL A LO PEDIDO NO SE DEBE SUMAR NI RESTAR | P20: 50 | Q20: 0 | R20: CUB MESA PUNTA TIBURON 3 LADOS
B21: 100 | C21: 100 | D21: CUB MESA 3L | E21: M | G21: 50 | H21: 0 | I21: CUB MESA 3L | P21: 50 | Q21: 0 | R21: CUB MESA PUNTA TIBURON 4 LADOS
B22: 100 | C22: 100 | D22: CUB MESA 4 LADOS | E22: N | I22: CUB MESA 4 LADOS | P22: 50 | Q22: 0 | R22: CUB PUNTA TIBURON 1 LADO
B23: 40 | C23: 150 | D23: CUB MESA FRENTE ESPAÑOL 2 LADOS | E23: O | G23: 50 | I23: CUB MESA FRENTE ESPAÑOL 2 LADOS | R23: CENEFA 1 LADO
B24: 140 | C24: 150 | D24: CUB MESA FRENTE ESPAÑOL 3 LADOS | E24: P | G24: 50 | I24: CUB MESA FRENTE ESPAÑOL 3 LADOS | R24: CENEFA 2 LADOS
B25: 150 | C25: 150 | D25: CUB MESA FRENTE ESPAÑOL 4 LADOS | E25: Q | G25: 50 | I25: CUB MESA FRENTE ESPAÑOL 4 LADOS | R25: CORNISA FRENTE ESPAÑOL 1 LADO
B26: 40 | C26: 77 | D26: CUB MESA PUNTA TIBURON 2 LADOS | E26: R | G26: 50 | I26: CUB MESA PUNTA TIBURON 2 LADOS | R26: CORNISA FRENTE ESPAÑOL 2 LADO
B27: 110 | C27: 77 | D27: CUB MESA PUNTA TIBURON 3 LADOS | E27: S | G27: 50 | I27: CUB MESA PUNTA TIBURON 3 LADOS | R27: CORNISA 180° 1LADO
B28: 120 | C28: 77 | D28: CUB MESA PUNTA TIBURON 4 LADOS | E28: T | G28: 50 | I28: CUB MESA PUNTA TIBURON 4 LADOS | R28: CORNISA 1LADO
B29: 40 | C29: 50 | D29: CUB PUNTA TIBURON 1 LADO | E29: U | G29: 50 | I29: CUB PUNTA TIBURON 1 LADO | R29: CORNISA 2 LADOS
B30: 40 | C30: 60 | D30: CUB S/R | E30: V | G30: 50 | I30: CUB S/R | R30: CORNISA PUNTA TIBURON 1 LADO
B31: 40 | C31: 100 | D31: CUB S/R FRENTE ESPAÑOL | E31: W | G31: 50 | I31: CUB S/R FRENTE ESPAÑOL | R31: CORNISA PUNTA TIBURON 2 LADOS
B32: 40 | C32: 60 | D32: CUB S/R R2 | E32: X | G32: 50 | I32: CUB S/R R2 | R32: PR2
B33: 40 | C33: 90 | D33: PR12 | E33: Y | G33: 50 | H33: -2 | I33: PR12 | R33: PR6
B34: 40 | C34: 90 | D34: PR19 | G34: 50 | H34: -2 | I34: PR19
B35: 40 | C35: 90 | D35: PR2 | E35: Z | G35: 50 | H35: -2 | I35: PR2 | R35: PR8
B36: 40 | C36: 90 | D36: PR6 | G36: 50 | H36: -2 | I36: PR6 | R36: PR12
B37: 40 | C37: 90 | D37: PR8 | G37: 50 | H37: -2 | I37: PR8 | R37: PR19
B48: 40 | C48: 150

Sheet CUBIERTA
L2: NO BORRAR REGLAS!!!!! SI NO LAS SABEN USAR NO BORREN ESTO POR FAVOR!!!!!
L3: SUSTRATO | N3: LAMINADO
D4: NOTA DE VENTA : | E4: ='4637'!G8 -> 7105 | L4: ALTO | M4: ANCHO | N4: ALTO | O4: ANCHO
D5: CLIENTE : | E5: ='4637'!C10 -> OSCAR LOPEZ | L5: =LOOKUP(G14,REGLAS!$I$4:$I$37,REGLAS!$G$4:$G$37)+K14 -> 2150 | M5: =LOOKUP(G14,REGLAS!$I$4:$I$37,REGLAS!$H$4:$H$37)+L14 -> 740 | N5: =LOOKUP(G27,REGLAS!$D$4:$D$37,REGLAS!$B$4:$B$37)+#REF! -> #REF! | O5: =LOOKUP(G27,REGLAS!$D$4:$D$37,REGLAS!$C$4:$C$37)+K27 -> 2160
D7: ='4637'!F11 -> FECHA LIMITE : | E7: ='4637'!G11 -> 45540
D8: FECHA ENTREGA: | G8: FD
B10: SUSTRATO
H11: 20
E12: ALTO | F12: ANCHO
B13: MATERIAL | C13: CANTIDAD | D13: CORTE | E13: 50 | G13: DESCRIPCIÓN | K13: ALTO | L13: ANCHO
A14: 1 | B14: MDF18MM | C14: =J14 -> 1 | E14: =K14+E$13 -> 2150 | F14: =L14+F$13 -> 740 | G14: =G27 -> CUBIERTA MESA 2 LADOS R2 | J14: =J27 -> 1 | K14: =K27 -> 2100 | L14: =L27 -> 740
A15: 2 | C15: =J15 -> 1 | E15: =K15+E$13 -> 2720 | F15: =L15+F$13 -> 630 | G15: =G28 -> CUB SIN RESPALDO R2 | J15: =J28 -> 1 | K15: =K28 -> 2670 | L15: =L28 -> 630
A16: 3 | C16: =J16 -> 1 | E16: =K16+E$13 -> 2345 | F16: =L16+F$13 -> 580 | G16: =G29 -> CUB SIN RESPALDO R2 | J16: =J29 -> 1 | K16: =K29 -> 2295 | L16: =L29 -> 580
A17: 4 | C17: =J17 -> 1 | E17: =K17+E$13 -> 1300 | F17: =L17+F$13 -> 450 | G17: =G30 -> CUB SIN RESPALDO R2 | J17: =J30 -> 1 | K17: =K30 -> 1250 | L17: =L30 -> 450
A18: 5 | C18: =J18 -> 1 | E18: =K18+E$13 -> 2345 | F18: 100 | G18: =G31 -> RESPALDO | J18: =J31 -> 1 | K18: =K31 -> 2295 | L18: =L31 -> 70
A19: 6 | C19: =J19 -> 1 | E19: =K19+E$13 -> 2720 | F19: 100 | G19: =G32 -> RESPALDO | J19: =J32 -> 1 | K19: =K32 -> 2670 | L19: =L32 -> 70
A20: 7 | C20: =J20 -> 1 | E20: =K20+E$13 -> 1300 | F20: 100 | G20: =G33 -> RESPALDO | J20: =J33 -> 1 | K20: =K33 -> 1250 | L20: =L33 -> 70
B23: LAMINADO
E25: ALTO | F25: ANCHO
B26: MATERIAL | C26: CANTIDAD | D26: CORTE | E26: 40 | F26: 70 | G26: DESCRIPCIÓN | K26: ALTO | L26: ANCHO
A27: 1 | B27: MDF18MM | C27: =J27 -> 1 | E27: =K27+E$26 -> 2140 | F27: 850 | G27: =D38 -> CUBIERTA MESA 2 LADOS R2 | J27: =C38 -> 1 | K27: =E38 -> 2100 | L27: =F38 -> 740
A28: 2 | C28: =J28 -> 1 | E28: =K28+E$26 -> 2710 | F28: =L28+F$26 -> 700 | G28: =D39 -> CUB SIN RESPALDO R2 | J28: =C39 -> 1 | K28: =E39 -> 2670 | L28: =F39 -> 630
A29: 3 | C29: =J29 -> 1 | E29: =K29+E$26 -> 2335 | F29: =L29+F$26 -> 650 | G29: =D40 -> CUB SIN RESPALDO R2 | J29: =C40 -> 1 | K29: =E40 -> 2295 | L29: =F40 -> 580
A30: 4 | C30: =J30 -> 1 | E30: =K30+E$26 -> 1290 | F30: =L30+F$26 -> 520 | G30: =D41 -> CUB SIN RESPALDO R2 | J30: =C41 -> 1 | K30: =E41 -> 1250 | L30: =F41 -> 450
A31: 5 | C31: =J31 -> 1 | E31: =K31+E$26 -> 2335 | F31: 130 | G31: =D42 -> RESPALDO | J31: =C42 -> 1 | K31: =E42 -> 2295 | L31: =F42 -> 70
A32: 6 | C32: =J32 -> 1 | E32: =K32+E$26 -> 2710 | F32: 130 | G32: =D43 -> RESPALDO | J32: =C43 -> 1 | K32: =E43 -> 2670 | L32: =F43 -> 70
A33: 7 | C33: =J33 -> 1 | E33: =K33+E$26 -> 1290 | F33: 130 | G33: =D44 -> RESPALDO | J33: =C44 -> 1 | K33: =E44 -> 1250 | L33: =F44 -> 70
C35: MEDIDAS ORIGINALES
B37: MATERIAL | C37: CANTIDAD | D37: DESCRIPCIÓN | E37: ALTO | F37: ANCHO | G37: COLOR
A38: 1 | B38: MDF18MM | C38: ='4637'!B22 -> 1 | D38: ='4637'!C22 -> CUBIERTA MESA 2 LADOS R2 | E38: ='4637'!D22 -> 2100 | F38: ='4637'!E22 -> 740 | G38: =G66 -> MARINA DI CARRARA
C39: ='4637'!B23 -> 1 | D39: ='4637'!C23 -> CUB SIN RESPALDO R2 | E39: ='4637'!D23 -> 2670 | F39: ='4637'!E23 -> 630 | G39: =G67 -> MARINA DI CARRARA
C40: ='4637'!B24 -> 1 | D40: ='4637'!C24 -> CUB SIN RESPALDO R2 | E40: ='4637'!D24 -> 2295 | F40: ='4637'!E24 -> 580 | G40: =G68 -> MARINA DI CARRARA
C41: ='4637'!B25 -> 1 | D41: ='4637'!C25 -> CUB SIN RESPALDO R2 | E41: ='4637'!D25 -> 1250 | F41: ='4637'!E25 -> 450 | G41: =G69 -> MARINA DI CARRARA
C42: ='4637'!B26 -> 1 | D42: ='4637'!C26 -> RESPALDO | E42: ='4637'!D26 -> 2295 | F42: ='4637'!E26 -> 70 | G42: =G70 -> MARINA DI CARRARA
C43: ='4637'!B27 -> 1 | D43: ='4637'!C27 -> RESPALDO | E43: ='4637'!D27 -> 2670 | F43: ='4637'!E27 -> 70 | G43: =G71 -> MARINA DI CARRARA
C44: ='4637'!B28 -> 1 | D44: ='4637'!C28 -> RESPALDO | E44: ='4637'!D28 -> 1250 | F44: ='4637'!E28 -> 70 | G44: =G72 -> MARINA DI CARRARA
D56: NOTA DE VENTA : | E56: ='4637'!G8 -> 7105
D57: CLIENTE : | E57: ='4637'!C10 -> OSCAR LOPEZ
D59: ='4637'!F11 -> FECHA LIMITE : | E59: ='4637'!G11 -> 45540 | G59: FERNANDO DONOSO
B62: PRODUCCIÓN
C64: DETALLE
C65: CANTIDAD | D65: CORTE | E65: ALTO | F65: ANCHO | G65: DESCRIPCION
B66: MDF18MM | C66: ='4637'!B22 -> 1 | D66: ='4637'!C22 -> CUBIERTA MESA 2 LADOS R2 | E66: ='4637'!D22 -> 2100 | F66: ='4637'!E22 -> 740 | G66: ='4637'!F22 -> MARINA DI CARRARA
C67: ='4637'!B23 -> 1 | D67: ='4637'!C23 -> CUB SIN RESPALDO R2 | E67: ='4637'!D23 -> 2670 | F67: ='4637'!E23 -> 630 | G67: ='4637'!F23 -> MARINA DI CARRARA
C68: ='4637'!B24 -> 1 | D68: ='4637'!C24 -> CUB SIN RESPALDO R2 | E68: ='4637'!D24 -> 2295 | F68: ='4637'!E24 -> 580 | G68: ='4637'!F24 -> MARINA DI CARRARA
C69: ='4637'!B25 -> 1 | D69: ='4637'!C25 -> CUB SIN RESPALDO R2 | E69: ='4637'!D25 -> 1250 | F69: ='4637'!E25 -> 450 | G69: ='4637'!F25 -> MARINA DI CARRARA
C70: ='4637'!B26 -> 1 | D70: ='4637'!C26 -> RESPALDO | E70: ='4637'!D26 -> 2295 | F70: ='4637'!E26 -> 70 | G70: ='4637'!F26 -> MARINA DI CARRARA
C71: ='4637'!B27 -> 1 | D71: ='4637'!C27 -> RESPALDO | E71: ='4637'!D27 -> 2670 | F71: ='4637'!E27 -> 70 | G71: ='4637'!F27 -> MARINA DI CARRARA
C72: ='4637'!B28 -> 1 | D72: ='4637'!C28 -> RESPALDO | E72: ='4637'!D28 -> 1250 | F72: ='4637'!E28 -> 70 | G72: ='4637'!F28 -> MARINA DI CARRARA
